myCalculatorPackage/__init__.py
myCalculatorPackage/division/__init__.py
myCalculatorPackage/division/divide.py
myCalculatorPackage/multiplication/__init__.py
myCalculatorPackage/multiplication/multiply.py
myCalculatorPackageerin-0.0.2.dist-info/LICENSE.txt
myCalculatorPackageerin-0.0.2.dist-info/METADATA
myCalculatorPackageerin-0.0.2.dist-info/WHEEL
myCalculatorPackageerin-0.0.2.dist-info/top_level.txt
myCalculatorPackageerin-0.0.2.dist-info/RECORD
